ml_demo_provider/__init__.py
ml_demo_provider/hooks/__init__.py
ml_demo_provider/hooks/ml_demo_framework.py
ml_demo_provider/operators/__init__.py
ml_demo_provider/operators/dataset_operators.py
ml_demo_provider/operators/model_deployment.py
ml_demo_provider/operators/model_training_operators.py
ml_demo_provider/operators/transform_operators.py
ml_demo_provider/operators/ml/__init__.py
ml_demo_provider/operators/ml/dataset_storage.py
ml_demo_provider/operators/ml/dataset_storage_minio.py
ml_demo_provider/operators/ml/demo_ml_pipeline.py
ml_demo_provider/operators/ml/ml_model.py
ml_demo_provider/operators/ml/model_trainer.py
ml_demo_provider/sensors/__init__.py
airflow_provider_demo_ml_framework-0.1.6.dist-info/LICENSE
airflow_provider_demo_ml_framework-0.1.6.dist-info/METADATA
airflow_provider_demo_ml_framework-0.1.6.dist-info/WHEEL
airflow_provider_demo_ml_framework-0.1.6.dist-info/entry_points.txt
airflow_provider_demo_ml_framework-0.1.6.dist-info/top_level.txt
airflow_provider_demo_ml_framework-0.1.6.dist-info/RECORD
